micropsi_challenge.py
micropsi_challenge-1.0.0.dist-info/LICENSE.txt
micropsi_challenge-1.0.0.dist-info/METADATA
micropsi_challenge-1.0.0.dist-info/WHEEL
micropsi_challenge-1.0.0.dist-info/top_level.txt
micropsi_challenge-1.0.0.dist-info/RECORD
