Metadata-Version: 2.1
Name: micropsi-challenge
Version: 1.0.0
Summary: Package to prove my skills
License: You allowed to do with this project whatever you want ;)
Keywords: micropsi,challenge
Requires-Python: >=3.9
License-File: LICENSE.txt
Provides-Extra: dev
Requires-Dist: pytest ; extra == 'dev'
